{"cameraMode":{"drawMode":0,"name":"Shaded","section":"Shading Mode"},"sceneLighting":true,"audioPlay":false,"sceneViewState":{"m_AlwaysRefresh":false,"showFog":true,"showSkybox":true,"showFlares":true,"showImageEffects":true,"showParticleSystems":true,"showVisualEffectGraphs":true,"m_FxEnabled":true},"in2DMode":false,"pivot":{"x":-15.271058082580567,"y":2.383601665496826,"z":1.2039902210235596},"rotation":{"x":0.013195891864597798,"y":-0.8480889201164246,"z":0.019392095506191255,"w":0.5306321978569031},"size":12.12435531616211,"orthographic":false}